project_odysseus/__init__.py
project_odysseus/cli.py
project_odysseus/knowledge_system.py
project_odysseus/templates.py
project_odysseus/applications/__init__.py
project_odysseus/applications/sdk.py
project_odysseus/applications/workshop.py
project_odysseus/applications/workshop_app.py
project_odysseus/connectors/__init__.py
project_odysseus/connectors/base.py
project_odysseus/connectors/implementations.py
project_odysseus/governance/__init__.py
project_odysseus/governance/access_control.py
project_odysseus/governance/data_lineage.py
project_odysseus/governance/logger.py
project_odysseus/governance/privacy_tools.py
project_odysseus/ontology/__init__.py
project_odysseus/ontology/advanced_models.py
project_odysseus/ontology/engine.py
project_odysseus/ontology/models.py
project_odysseus-1.0.0.dist-info/licenses/LICENSE
project_odysseus-1.0.0.dist-info/METADATA
project_odysseus-1.0.0.dist-info/WHEEL
project_odysseus-1.0.0.dist-info/entry_points.txt
project_odysseus-1.0.0.dist-info/top_level.txt
project_odysseus-1.0.0.dist-info/RECORD
