Metadata-Version: 2.4
Name: project-odysseus
Version: 1.0.0
Summary: Palantir-style Ontology Infrastructure Library for Enterprise Data Intelligence
Author-email: Project Odysseus Team <odysseus@example.com>
License-Expression: MIT
Project-URL: Homepage, https://github.com/project-odysseus/odysseus
Project-URL: Documentation, https://odysseus.readthedocs.io
Project-URL: Repository, https://github.com/project-odysseus/odysseus
Project-URL: Bug Tracker, https://github.com/project-odysseus/odysseus/issues
Keywords: ontology,data-intelligence,knowledge-graph,palantir,enterprise
Classifier: Development Status :: 4 - Beta
Classifier: Intended Audience :: Developers
Classifier: Intended Audience :: Information Technology
Classifier: Operating System :: OS Independent
Classifier: Programming Language :: Python :: 3
Classifier: Programming Language :: Python :: 3.8
Classifier: Programming Language :: Python :: 3.9
Classifier: Programming Language :: Python :: 3.10
Classifier: Programming Language :: Python :: 3.11
Classifier: Programming Language :: Python :: 3.12
Classifier: Topic :: Scientific/Engineering :: Information Analysis
Classifier: Topic :: Software Development :: Libraries :: Python Modules
Requires-Python: >=3.8
License-File: LICENSE
Requires-Dist: pandas>=1.5.0
Requires-Dist: rdflib>=6.0.0
Requires-Dist: streamlit>=1.20.0
Requires-Dist: plotly>=5.0.0
Requires-Dist: networkx>=3.0.0
Requires-Dist: requests>=2.25.0
Requires-Dist: numpy>=1.20.0
Requires-Dist: beautifulsoup4>=4.9.0
Requires-Dist: spacy>=3.4.0
Requires-Dist: duckduckgo-search>=3.0.0
Provides-Extra: dev
Requires-Dist: pytest>=7.0.0; extra == "dev"
Requires-Dist: pytest-cov>=4.0.0; extra == "dev"
Requires-Dist: black>=22.0.0; extra == "dev"
Requires-Dist: flake8>=5.0.0; extra == "dev"
Requires-Dist: mypy>=1.0.0; extra == "dev"
Requires-Dist: sphinx>=5.0.0; extra == "dev"
Requires-Dist: sphinx-rtd-theme>=1.0.0; extra == "dev"
Provides-Extra: web
Requires-Dist: streamlit>=1.20.0; extra == "web"
Requires-Dist: plotly>=5.0.0; extra == "web"
Requires-Dist: dash>=2.0.0; extra == "web"
Provides-Extra: enterprise
Requires-Dist: sqlalchemy>=1.4.0; extra == "enterprise"
Requires-Dist: psycopg2-binary>=2.9.0; extra == "enterprise"
Requires-Dist: redis>=4.0.0; extra == "enterprise"
Requires-Dist: celery>=5.0.0; extra == "enterprise"
Requires-Dist: kafka-python>=2.0.0; extra == "enterprise"
Dynamic: license-file
